Workbook

Sheet Dashboard
B2: SAKO MAKMUR WIFI - NETOS EXECUTIVE DASHBOARD
B3: Konsorsium Starlink Hybrid FO | Monitoring Siklus Operasional & Dividen Investor
B5: Siklus Aktif: Oktober 2026 | Tagihan Terbit: Tgl 10 Okt • Jatuh Tempo: Tgl 18 Okt • Tutup Buku: Tgl 25 Okt
B7: 1. RINGKASAN PELANGGAN & OMZET BULAN BERJALAN (OKTOBER 2026)
B8: TOTAL PELANGGAN | D8: PELANGGAN LUNAS | F8: BELUM BAYAR | H8: PERSENTASE LUNAS
B9: =COUNTA(Pelanggan!B6:B22) | D9: =COUNTIF(Pelanggan!I6:I22, "Lunas") | F9: =COUNTIF(Pelanggan!I6:I22, "Belum Bayar") | H9: =D9/B9
B11: 2. ARUS KAS & BEBAN OPERASIONAL (OPEX)
B12: Parameter Keuangan | D12: Keterangan / Rumus | F12: Nominal (Rp) | H12: Status / Catatan
B13: Kas Masuk Terkumpul (Omzet Riil) | D13: Total iuran dari pelanggan yang sudah lunas | F13: =SUMIF(Pelanggan!I6:I22, "Lunas", Pelanggan!F6:F22) | H13: Terkumpul di Bendahara
B14: Potensi Kas Penuh (100%) | D14: Kapasitas penuh 17 user jika seluruhnya bayar | F14: =SUM(Pelanggan!F6:F22) | H14: Target Kapasitas Penuh
B15: Piutang Tagihan Tertunggak | D15: Tagihan yang belum dibayarkan (Belum Bayar) | F15: =F14-F13 | H15: Jatuh tempo tgl 18
B16: Total Beban OPEX Rutin | D16: Starlink + PLN + Gaji Operator + Marketing + Jasa Tagih | F16: =Pengeluaran_OPEX!E12 | H16: Beban Operasional Berjalan
B17: Cadangan Kas Siaga (10%) | D17: 10% dialokasikan ke Rekening Cadangan Maintenance | F17: =F13*0.1 | H17: Tabungan Darurat Jaringan
B18: Laba Bersih Operasional (Net Profit) | D18: Kas Masuk - Total Beban OPEX - Cadangan Kas 10% | F18: =MAX(0, F13-F16-F17) | H18: Siap Dibagikan Tgl 25
B20: 3. HAK DIVIDEN INVESTOR KONSORSIUM (OKTOBER 2026)
B21: Investor | C21: Peran | D21: Modal Disetor (Rp) | E21: Saham (%) | F21: Estimasi Dividen (Rp) | G21: Penjamin Aset Fisik (Rp) | H21: Status Transfer
B22: Ahmad Fauzi | C22: Investor | D22: 15000000 | E22: 0.6 | F22: =F18*E22 | G22: =Aset_CAPEX!G17*E22 | H22: Pending (Tgl 25 Okt)
B23: Anwar Khadafi Saimona | C23: Investor | D23: 5000000 | E23: 0.2 | F23: =F18*E23 | G23: =Aset_CAPEX!G17*E23 | H23: Pending (Tgl 25 Okt)
B24: Tri Wahyono | C24: Managing Owner | D24: 5000000 | E24: 0.2 | F24: =F18*E24 | G24: =Aset_CAPEX!G17*E24 | H24: Pending (Tgl 25 Okt)
B25: TOTAL KONSORSIUM | C25: 3 Anggota | D25: =SUM(D22:D24) | E25: =SUM(E22:E24) | F25: =SUM(F22:F24) | G25: =SUM(G22:G24) | H25: Siap Bagi 25 Okt
B27: 4. CATATAN RESMI TUTUP BUKU SEBELUMNYA (SEPTEMBER 2026 - LUNAS TUNTAS ✅)
B28: Arsip September 2026: Omzet Rp 2.600.000 | OPEX Rp 2.015.000 | Cadangan Kas Rp 260.000 | Laba Bersih Rp 585.000
B29: Dividen Lunas Dibagikan: Ahmad Fauzi Rp 351.000 (60%) • Anwar Khadafi S. Rp 117.000 (20%) • Tri Wahyono Rp 117.000 (20%)

Sheet Pelanggan
B2: DAFTAR PELANGGAN AKTIF SAKO MAKMUR WIFI
B3: Total 17 Pelanggan | Status Pembayaran Siklus Oktober 2026 (Jatuh Tempo Tgl 18)
A5: No | B5: Username PPPoE | C5: Nama Pelanggan | D5: Paket Internet | E5: Kecepatan | F5: Tarif Bulanan (Rp) | G5: Biaya Pasang (Rp) | H5: Jatuh Tempo | I5: Status Pembayaran | J5: Metode Pembayaran | K5: Tgl Bayar Terakhir | L5: Status Router | M5: Alamat / Dusun
A6: 1 | B6: topik-123 | C6: Topik | D6: Paket Up to 5 Mbps | E6: 5 Mbps | F6: 250000 | G6: 0 | H6: 18 | I6: Belum Bayar | J6: - | K6: 2026-09-25 | L6: Aktif | M6: Sako Makmur
A7: 2 | B7: sidiq-123 | C7: Sidiq | D7: Paket Up to 5 Mbps | E7: 5 Mbps | F7: 250000 | G7: 0 | H7: 18 | I7: Belum Bayar | J7: - | K7: 2026-09-25 | L7: Aktif | M7: Sako Makmur
A8: 3 | B8: jaka-123 | C8: Jaka | D8: Paket Up to 5 Mbps | E8: 5 Mbps | F8: 200000 | G8: 0 | H8: 18 | I8: Belum Bayar | J8: - | K8: 2026-09-25 | L8: Aktif | M8: Sako Makmur
A9: 4 | B9: gunawan-123 | C9: Mbah Gun | D9: Paket Up to 5 Mbps | E9: 5 Mbps | F9: 250000 | G9: 0 | H9: 18 | I9: Belum Bayar | J9: - | K9: 2026-09-25 | L9: Aktif | M9: Sako Makmur
A10: 5 | B10: ropei-123 | C10: Ropei | D10: Paket Up to 5 Mbps | E10: 5 Mbps | F10: 200000 | G10: 0 | H10: 18 | I10: Belum Bayar | J10: - | K10: 2026-09-25 | L10: Aktif | M10: Sako Makmur
A11: 6 | B11: sis-123 | C11: Mas Sis | D11: Paket Up to 8 Mbps | E11: 8 Mbps | F11: 250000 | G11: 0 | H11: 18 | I11: Belum Bayar | J11: - | K11: 2026-10-02 | L11: Aktif | M11: Sako Makmur
A12: 7 | B12: toni-123 | C12: Mas Toni | D12: Paket Up to 5 Mbps | E12: 5 Mbps | F12: 200000 | G12: 0 | H12: 18 | I12: Belum Bayar | J12: - | K12: 2026-09-25 | L12: Aktif | M12: Sako Makmur
A13: 8 | B13: user-test123 | C13: VERA | D13: Paket Up to 5 Mbps | E13: 5 Mbps | F13: 250000 | G13: 0 | H13: 18 | I13: Belum Bayar | J13: - | K13: 2026-09-25 | L13: Aktif | M13: Sako Makmur
A14: 9 | B14: user-test | C14: Tembong | D14: Paket Up to 5 Mbps | E14: 5 Mbps | F14: 200000 | G14: 0 | H14: 18 | I14: Belum Bayar | J14: - | K14: 2026-09-25 | L14: Aktif | M14: Sako Makmur
A15: 10 | B15: user-test12 | C15: Yayan | D15: Paket Up to 5 Mbps | E15: 5 Mbps | F15: 250000 | G15: 0 | H15: 18 | I15: Belum Bayar | J15: - | K15: 2026-09-25 | L15: Aktif | M15: Sako Makmur
A16: 11 | B16: user-test1234 | C16: Acim | D16: Paket Up to 5 Mbps | E16: 5 Mbps | F16: 250000 | G16: 0 | H16: 18 | I16: Belum Bayar | J16: - | K16: 2026-09-25 | L16: Aktif | M16: Sako Makmur
A17: 12 | B17: user-test12345 | C17: BuSupri | D17: Paket Up to 5 Mbps | E17: 5 Mbps | F17: 250000 | G17: 0 | H17: 18 | I17: Belum Bayar | J17: - | K17: 2026-09-25 | L17: Aktif | M17: Sako Makmur
... A22: 17 | B22: iyeng-123 | C22: Wak Iyeng | D22: Paket Up to 5 Mbps | E22: 5 Mbps | F22: 200000 | G22: 0 | H22: 18 | I22: Belum Bayar | J22: - | K22: 2026-10-02 | L22: Aktif | M22: Dusun 2 RT 4
B23: TOTAL | C23: 17 Pelanggan | F23: =SUM(F6:F22) | G23: =SUM(G6:G22)

Sheet Pengeluaran_OPEX
B2: BUKU KAS BEBAN OPERASIONAL (OPEX) SAKO MAKMUR WIFI
B3: Rincian Biaya Rutin Bulanan & Buku Kas Harian Pengeluaran Jaringan
B5: A. REKAPITULASI BEBAN OPERASIONAL RUTIN BULANAN (OKTOBER 2026)
A6: No | B6: Komponen Biaya | C6: Kategori | D6: Tipe Beban | E6: Nominal (Rp) | F6: Keterangan / Rumus
A7: 1 | B7: Langganan Starlink Standard | C7: Internet Backhaul | D7: Tetap (Fixed) | E7: 850000 | F7: Tagihan bulanan Starlink Standard Kit
A8: 2 | B8: Listrik & Token PLN Node RT 01 | C8: Power & Utility | D8: Tetap (Fixed) | E8: 300000 | F8: Daya node pusat & UPS RT 01
A9: 3 | B9: Gaji Operator Lapangan & Maintenance | C9: SDM Teknis | D9: Tetap (Fixed) | E9: 500000 | F9: Maintenance berkala & perbaikan jalur
A10: 4 | B10: Komisi Marketing Rutin Bulanan | C10: Pemasaran | D10: Tetap (Fixed) | E10: 50000 | F10: Sosialisasi & akuisisi pelanggan
A11: 5 | B11: Jasa Tagih Lapangan (Rp 5.000 / User Lunas) | C11: Operasional Tagih | D11: Variabel | E11: =COUNTIF(Pelanggan!I6:I22, "Lunas")*5000 | F11: Otomatis dihitung Rp 5.000 per user yang lunas
B12: TOTAL BEBAN OPEX RUTIN | E12: =SUM(E7:E11) | F12: Total beban yang wajib dicover oleh kas masuk iuran
B14: B. LOG BUKU KAS HARIAN PENGELUARAN (REAL TIME TRANSACTION LOG)
A15: ID Transaksi | B15: Tanggal | C15: Kategori Beban | D15: Nominal (Rp) | E15: Sumber Dana | F15: Keterangan Pengeluaran
A16: EXP-202610-01 | B16: 2026-10-01 | C16: Langganan Starlink | D16: 850000 | E16: Kas Operasional | F16: Tagihan bulanan Starlink Standard Kit (Oktober 2026)
A17: EXP-202610-02 | B17: 2026-10-01 | C17: Listrik & Token PLN | D17: 300000 | E17: Kas Operasional | F17: Token listrik PLN Node RT 01 & UPS (Oktober 2026)
A18: EXP-202610-03 | B18: 2026-10-01 | C18: Gaji Operator | D18: 500000 | E18: Kas Operasional | F18: Uang operasional & maintenance jaringan (Oktober 2026)
A19: EXP-202610-04 | B19: 2026-10-01 | C19: Komisi Marketing | D19: 50000 | E19: Kas Operasional | F19: Komisi marketing rutin bulanan (Oktober 2026)
A20: EXP-202609-01 | B20: 2026-09-19 | C20: Langganan Starlink | D20: 850000 | E20: Kas Operasional | F20: Arsip: Tagihan Starlink September (Tutup Buku)
A21: EXP-202609-02 | B21: 2026-09-19 | C21: Listrik & Token PLN | D21: 250000 | E21: Kas Operasional | F21: Arsip: Token PLN September (Tutup Buku)
A22: EXP-202609-03 | B22: 2026-09-19 | C22: Gaji Operator | D22: 500000 | E22: Kas Operasional | F22: Arsip: Operator September (Tutup Buku)
A23: EXP-202609-04 | B23: 2026-09-19 | C23: Bensin & Patroli | D23: 75000 | E23: Kas Operasional | F23: Arsip: Patroli kabel FO & tiang September (Tutup Buku)
A24: EXP-202609-05 | B24: 2026-09-19 | C24: Komisi Marketing | D24: 50000 | E24: Kas Operasional | F24: Arsip: Marketing September (Tutup Buku)
A25: EXP-202609-06 | B25: 2026-09-19 | C25: Jasa Tagih | D25: 55000 | E25: Kas Operasional | F25: Arsip: Fee kolektor 11 user September (Tutup Buku)

Sheet Struktur_Investor
B2: STRUKTUR PERMODALAN & INVESTOR KONSORSIUM
B3: Konsorsium Sako Makmur WiFi | Total Modal Rp 25.000.000 | Kontrak 12 Bulan (Sep 2026 - Agu 2027)
A5: No | B5: Nama Pemegang Saham | C5: Peran Konsorsium | D5: Modal Disetor (Rp) | E5: Persentase Saham | F5: Penjamin Aset Fisik (Rp) | G5: Estimasi Dividen Bln Ini | H5: Total Dividen Diterima | I5: Masa Kontrak | J5: Status Kontrak | K5: Rekening Bank | L5: No Rekening & Atas Nama
A6: 1 | B6: Ahmad Fauzi | C6: Investor | D6: 15000000 | E6: 0.6 | F6: =Aset_CAPEX!G17*E6 | G6: =Dashboard!F18*E6 | H6: 351000 | I6: 12 Bulan | J6: Bulan ke-2 dari 12 | K6: BRI | L6: Ahmad Fauzi
A7: 2 | B7: Anwar Khadafi Saimona | C7: Investor | D7: 5000000 | E7: 0.2 | F7: =Aset_CAPEX!G17*E7 | G7: =Dashboard!F18*E7 | H7: 117000 | I7: 12 Bulan | J7: Bulan ke-2 dari 12 | K7: BRI | L7: Anwar Khadafi Saimona
A8: 3 | B8: Tri Wahyono | C8: Managing Owner | D8: 5000000 | E8: 0.2 | F8: =Aset_CAPEX!G17*E8 | G8: =Dashboard!F18*E8 | H8: 117000 | I8: 12 Bulan | J8: Bulan ke-2 dari 12 | K8: BCA | L8: Tri Wahyono
B9: TOTAL KONSORSIUM | C9: 3 Anggota | D9: =SUM(D6:D8) | E9: =SUM(E6:E8) | F9: =SUM(F6:F8) | G9: =SUM(G6:G8) | H9: =SUM(H6:H8)

Sheet Aset_CAPEX
B2: DAFTAR BELANJA MODAL & ASET PENJAMIN (CAPEX)
B3: Aset Fisik Jaringan Sako Makmur WiFi Sebagai Penjamin Modal Investor Konsorsium
B5: TOTAL MODAL INVESTOR | D5: TOTAL BELANJA ASET FISIK | F5: SISA KAS MODAL AWAL | H5: STATUS COVER PENJAMIN
B6: =Struktur_Investor!D9 | D6: =G17 | F6: =B6-D6 | H6: =D6/B6
A8: No | B8: Nama Perangkat / Barang | C8: Kategori Aset | D8: Volume | E8: Satuan | F8: Harga Satuan (Rp) | G8: Total Nilai (Rp) | H8: Status Fisik
A9: 1 | B9: Starlink Gen 3 Standard Kit & Mount | C9: Starlink & Backhaul | D9: 1 | E9: unit | F9: 7800000 | G9: =D9*F9 | H9: Aktif Operasional
A10: 2 | B10: MikroTik Cloud Router RB750Gr3 / RB4011 | C10: MikroTik & Core | D10: 1 | E10: unit | F10: 1350000 | G10: =D10*F10 | H10: Aktif Normal
A11: 3 | B11: Kabel Dropcore FO 1 Core 3 Seling (1000m) | C11: Kabel & Distribusi | D11: 2 | E11: roll | F11: 1100000 | G11: =D11*F11 | H11: Terpasang di Tiang
A12: 4 | B12: Media Converter HTB 3100 A/B + Fast Connector | C12: Kabel & Distribusi | D12: 10 | E12: pasang | F12: 165000 | G12: =D12*F12 | H12: Terpasang
A13: 5 | B13: UPS ICA 1200VA + Aki Eksternal Cadangan Node | C13: Power & Backup | D13: 1 | E13: unit | F13: 2800000 | G13: =D13*F13 | H13: Aktif Backup
A14: 6 | B14: Mini ODP 8 Core, Pigtail, Protection Box | C14: Kabel & Distribusi | D14: 4 | E14: box | F14: 225000 | G14: =D14*F14 | H14: Terpasang
A15: 7 | B15: Tiang Besi Galvanis 6 Meter & Klem Tarik | C15: Lainnya & Tiang | D15: 5 | E15: batang | F15: 320000 | G15: =D15*F15 | H15: Tertanam Kokoh
A16: 8 | B16: Jasa Tarik Kabel Backbone & Instalasi Awal Jaringan | C16: Jasa & Instalasi | D16: 1 | E16: lot | F16: 4000000 | G16: =D16*F16 | H16: Selesai 100%
B17: TOTAL BELANJA ASET MODAL (CAPEX) | D17: =SUM(D9:D16) | E17: Item | G17: =SUM(G9:G16) | H17: 100% Aman Terverifikasi

Sheet Tutup_Buku_Histori
B2: ARSIP RESMI TUTUP BUKU BULANAN & HISTORI DIVIDEN
B3: Rekam Jejak Pembagian Laba Bersih Konsorsium Setiap Tanggal 25
A5: No | B5: Periode | C5: Tgl Tutup | D5: Ditutup Oleh | E5: User Lunas | F5: Omzet Riil (Rp) | G5: Total OPEX (Rp) | H5: Cadangan Kas 10% | I5: Laba Bersih (Rp) | J5: Dividen Ahmad Fauzi (60%) | K5: Dividen Anwar K. (20%) | L5: Dividen Tri W. (20%) | M5: Status Penyaluran
A6: 1 | B6: September 2026 | C6: 2026-09-20 | D6: Tri Wahyono | E6: 11 | F6: 2600000 | G6: 2015000 | H6: 260000 | I6: 585000 | J6: 351000 | K6: 117000 | L6: 117000 | M6: LUNAS DITRANSFER ✅
A7: 2 | B7: Oktober 2026 | C7: 2026-10-25 | D7: Tri Wahyono | E7: =Dashboard!D9 | F7: =Dashboard!F13 | G7: =Dashboard!F16 | H7: =Dashboard!F17 | I7: =Dashboard!F18 | J7: =Dashboard!F22 | K7: =Dashboard!F23 | L7: =Dashboard!F24 | M7: BERJALAN (Tgl 25 Okt)

Sheet Simulator_Finansial
B2: SIMULATOR FINANSIAL & PROYEKSI BEP SAKO MAKMUR WIFI
B3: Eksperimen Skenario Jumlah Pelanggan, ARPU, Biaya OPEX, dan Waktu Balik Modal
B5: PARAMETER SIMULASI (DAPAT DIUBAH) | F5: PROYEKSI HASIL KEUANGAN & DIVIDEN
B6: Target Jumlah Pelanggan (User) | D6: 35 | F6: Proyeksi Omzet Kotor (Gross) | H6: =D6*D7
B7: ARPU Rata-rata per User (Rp) | D7: 150000 | F7: Proyeksi Fee Tagih Kolektor | H7: =D6*D11
B8: Biaya Bulanan Starlink (Rp) | D8: 850000 | F8: Cadangan Kas Siaga (10%) | H8: =H6*D13
B9: Biaya Listrik PLN Node (Rp) | D9: 300000 | F9: Total Beban OPEX | H9: =D8+D9+D10+D12+H7+H8
B10: Gaji Operator Lapangan (Rp) | D10: 1000000 | F10: Estimasi Laba Bersih (Net) | H10: =MAX(0, H6-H9)
B11: Jasa Tagih per Pelanggan (Rp) | D11: 5000 | F11: Profit Margin (%) | H11: =H10/H6
B12: Komisi Marketing Bulanan (Rp) | D12: 250000
B13: Cadangan Kas Maintenance (%) | D13: 0.1 | F13: Dividen Ahmad Fauzi (60%) | H13: =H10*0.60
F14: Dividen Anwar Khadafi S. (20%) | H14: =H10*0.20
F15: Dividen Tri Wahyono (20%) | H15: =H10*0.20
F17: Proyeksi Balik Modal (BEP) | H17: =IF(H10>0, Aset_CAPEX!G17/H10, "Tidak BEP")

Sheet Kwitansi_Pelanggan
B2: GENERATOR KWITANSI PEMBAYARAN INTERNET SAKO MAKMUR WIFI
B3: Pilih Username PPPoE pelanggan di sel D5 untuk mencetak struk resmi otomatis
B5: Pilih Username Pelanggan: | D5: sidiq-123
B7: SAKO MAKMUR WIFI - BUKTI PEMBAYARAN IURAN INTERNET RESMI
B8: Konsorsium Sako Makmur WiFi | Layanan Internet Desa Berkecepatan Tinggi
B10: No. Kuitansi | C10: ="SMW-202610-" & UPPER(D5)
B11: Tanggal Terbit | C11: =TODAY()
B12: Periode Langganan | C12: Oktober 2026
B13: Username PPPoE | C13: =D5
B14: Nama Pelanggan | C14: =VLOOKUP(D5, Pelanggan!B6:M22, 2, FALSE)
B15: Paket Layanan | C15: =VLOOKUP(D5, Pelanggan!B6:M22, 3, FALSE)
B16: Bandwidth / Kecepatan | C16: =VLOOKUP(D5, Pelanggan!B6:M22, 4, FALSE)
B17: Alamat / Lokasi | C17: =VLOOKUP(D5, Pelanggan!B6:M22, 12, FALSE)
B18: Jatuh Tempo | C18: Tanggal 18 Oktober 2026
B19: Status Pembayaran | C19: =VLOOKUP(D5, Pelanggan!B6:M22, 8, FALSE)
B20: Metode Pembayaran | C20: =VLOOKUP(D5, Pelanggan!B6:M22, 9, FALSE)
B21: Total Tagihan / Iuran | C21: =VLOOKUP(D5, Pelanggan!B6:M22, 5, FALSE)
B23: Diterima & Diverifikasi oleh Bendahara / Pengelola (Mas Tri Wahyono)
B24: Simpan kuitansi ini sebagai bukti pembayaran sah iuran bulanan internet Anda. Terima kasih!

Sheet Format_Laporan_WhatsApp
B2: TEMPLATE LAPORAN WHATSAPP KONSORSIUM (FORMULA DINAMIS)
B3: Teks laporan otomatis tersusun dari data riil. Siap disalin (Copy-Paste) ke WhatsApp Mas Tri.
B5: A. DRAF LAPORAN PROGRES OKTOBER 2026 (UNTUK REVIEW MAS TRI)
B6: ⚠️ PERINGATAN SOP: Kirimkan draf ini HANYA ke WhatsApp Mas Tri untuk review. DILARANG kirim ke grup investor!
B8: ="📊 *LAPORAN PROGRES PENAGIHAN SAKO MAKMUR WIFI*" & CHAR(10) & "🗓️ *Periode:* Oktober 2026 (Siklus Aktif)" & CHAR(10) & "──────────────" & CHAR(10) & "👥 *Pelanggan Lunas:* " & Dashboard!D9 & " dari " & Dashboard!B9 & " User (" & TEXT(Dashboard!H9, "0.0%") & ")" & CHAR(10) & "💵 *Kas Masuk Terkumpul:* " & TEXT(Dashboard!F13, "Rp #,##0") & CHAR(10) & "🎯 *Target Potensi Penuh:* " & TEXT(Dashboard!F14, "Rp #,##0") & CHAR(10) & "📉 *Total Beban OPEX:* " & TEXT(Dashboard!F16, "Rp #,##0") & CHAR(10) & "🛡️ *Cadangan Kas (10%):* " & TEXT(Dashboard!F17, "Rp #,##0") & CHAR(10) & "💰 *Estimasi Laba Bersih:* " & TEXT(Dashboard!F18, "Rp #,##0") & CHAR(10) & "──────────────" & CHAR(10) & "🤝 *Proyeksi Dividen:* Fauzi (60%) " & TEXT(Dashboard!F22, "Rp #,##0") & " | Anwar (20%) " & TEXT(Dashboard!F23, "Rp #,##0") & " | Tri (20%) " & TEXT(Dashboard!F24, "Rp #,##0") & CHAR(10) & "⚠️ Catatan: Draf internal untuk Mas Tri sebelum verifikasi kas fisik."
B18: B. TEKS RESMI TUTUP BUKU SEPTEMBER 2026 (ARSIP LUNAS DITRANSFER)
B19: 📊 *LAPORAN RESMI KEUANGAN & DIVIDEN SAKO MAKMUR WIFI* 🗓️ *Periode:* September 2026 🔒 *Status:* TELAH DITUTUP & LUNAS DITRANSFER ✅ Ditutup oleh: Tri Wahyono (Managing Owner) ─────────────────────── 👥 *Pelanggan Lunas:* 11 dari 11 User Terdaftar 💵 *Total Kas Masuk:* Rp 2.600.000 📉 *Total Beban OPEX:* Rp 2.015.000 🛡️ *Dana Cadangan (10%):* Rp 260.000 ─────────────────────── 💰 *LABA BERSIH DIBAGIKAN:* Rp 585.000 🤝 *STATUS PENCAIRAN DIVIDEN:* 1. *Ahmad Fauzi* (60%): Rp 351.000 [LUNAS DITRANSFER ✅] 2. *Anwar Khadafi Saimona* (20%): Rp 117.000 [LUNAS DITRANSFER ✅] 3. *Tri Wahyono* (20%): Rp 117.000 [LUNAS DITRANSFER ✅] ─────────────────────── ✅ *Seluruh dividen periode September telah selesai ditransfer ke rekening masing-masing investor.*

Sheet Aturan_Bisnis_SOP
B2: STANDAR OPERASIONAL PROSEDUR & ATURAN BISNIS KONSORSIUM
B3: Pedoman Manajemen Kas, Penagihan, Proteksi Investor, dan Siklus Tutup Buku Sako Makmur WiFi
B5: 1. SIKLUS TANGGAL EMAS OPERASIONAL BULANAN
B6: Tanggal 10 | C6: Penerbitan Invoice Resmi: Tagihan dicetak / dibagikan ke seluruh pelanggan aktif.
B7: Tanggal 18 | C7: Batas Jatuh Tempo: Batas akhir pembayaran pelanggan. Pelanggan yang belum lunas disiapkan penagihan intensif / isolir manual.
B8: Tanggal 25 | C8: Tutup Buku Resmi & Penyaluran Dividen: Laba bersih dihitung dan ditransfer langsung ke rekening 3 investor.
B10: 2. MANAJEMEN TIGA KANTONG KAS (3-POCKET CASH FLOW)
B11: Kantong 1: Kas Operasional (OPEX) | C11: Membayar kewajiban rutin: Starlink Rp 850k, PLN Rp 300k, Operator Rp 500k, Marketing Rp 50k, Fee Kolektor Rp 5k/user.
B12: Kantong 2: Cadangan Kas Maintenance (10%) | C12: Wajib disisihkan 10% dari omzet kas masuk ke rekening khusus cadangan untuk mitigasi petir, putus fiber, atau servis alat.
B13: Kantong 3: Laba Bersih Siap Bagi (Dividen) | C13: Sisa kas bersih setelah dikurangi OPEX dan Cadangan Kas 10%. Dibagikan 60% Ahmad Fauzi, 20% Anwar Khadafi, 20% Tri Wahyono.
B15: 3. PENJAMINAN MODAL INVESTOR (CAPEX GUARANTEE)
B16: Aset Fisik Jaringan | C16: Seluruh modal disetor (Rp 25.000.000) terwujud dalam bentuk aset fisik riil (Dish Starlink Gen 3, Router MikroTik, 2000m Dropcore FO, ODP, Tiang, UPS ICA).
B17: Hak Investor | C17: Aset fisik berstatus jaminan modal investor jika konsorsium mengalami force majeure, proporsional sesuai saham masing-masing.
B19: 4. PROTOKOL DISTRIBUSI LAPORAN KONSORSIUM (SOP ANDINI / MAS TRI)
B20: Human-in-the-Loop Review | C20: Sistem / Bot Andini DILARANG mengirimkan laporan keuangan langsung ke grup WhatsApp investor.
B21: Validasi Pengelola | C21: Seluruh laporan wajib dikirimkan ke WhatsApp pribadi Mas Tri terlebih dahulu untuk direview dan diverifikasi kas fisiknya.
B22: Transparansi Resmi | C22: Setelah disetujui Mas Tri, barulah laporan resmi dibagikan ke grup investor konsorsium.
